README.md
setup.cfg
setup.py
./pyfmc/__init__.py
./pyfmc/exceptions.py
./pyfmc/common/__init__.py
./pyfmc/common/historical_data.py
./pyfmc/simulations/__init__.py
./pyfmc/simulations/gbm.py
pyfmc.egg-info/PKG-INFO
pyfmc.egg-info/SOURCES.txt
pyfmc.egg-info/dependency_links.txt
pyfmc.egg-info/requires.txt
pyfmc.egg-info/top_level.txt