Metadata-Version: 2.1
Name: pyfmc
Version: 0.1.1
Summary: Finance Monte-Carlo Simulation using PyTorch
Home-page: https://github.com/ethanlee928/pyfmc
Author: Ethan Lee
Author-email: ethan2000.el@gmail.com
License: UNKNOWN
Platform: UNKNOWN
Classifier: Programming Language :: Python :: 3.8
Classifier: License :: OSI Approved :: MIT License
Classifier: Operating System :: OS Independent
